{"nextToken":"","spotPriceHistorySet":[{"availabilityZone":"us-east-1a","instanceType":"c3.4xlarge","productDescription":"Linux/UNIX (Amazon VPC)","spotPrice":"1.680000","timestamp":1.403126243E9},{"availabilityZone":"us-east-1d","instanceType":"c3.8xlarge","productDescription":"Linux/UNIX (Amazon VPC)","spotPrice":"0.500000","timestamp":1.403126233E9},{"availabilityZone":"us-east-1d","instanceType":"cr1.8xlarge","productDescription":"Linux/UNIX","spotPrice":"0.313500","timestamp":1.403126233E9},{"availabilityZone":"us-east-1a","instanceType":"cr1.8xlarge","productDescription":"Linux/UNIX","spotPrice":"0.301600","timestamp":1.403126233E9},{"availabilityZone":"us-east-1d","instanceType":"c3.2xlarge","productDescription":"Linux/UNIX","spotPrice":"0.064800","timestamp":1.40312623E9},{"availabilityZone":"us-east-1a","instanceType":"c3.2xlarge","productDescription":"SUSE Linux","spotPrice":"0.164600","timestamp":1.403126228E9},{"availabilityZone":"us-east-1d","instanceType":"m3.2xlarge","productDescription":"Linux/UNIX","spotPrice":"0.064700","timestamp":1.403126139E9},{"availabilityZone":"us-east-1d","instanceType":"m3.2xlarge","productDescription":"SUSE Linux","spotPrice":"0.123800","timestamp":1.403126139E9},{"availabilityZone":"us-east-1d","instanceType":"m3.xlarge","productDescription":"Windows","spotPrice":"0.138500","timestamp":1.403126134E9},{"availabilityZone":"us-east-1d","instanceType":"cc2.8xlarge","productDescription":"Windows (Amazon VPC)","spotPrice":"0.428100","timestamp":1.403126134E9},{"availabilityZone":"us-east-1d","instanceType":"m3.2xlarge","productDescription":"SUSE Linux (Amazon VPC)","spotPrice":"0.123200","timestamp":1.403126126E9},{"availabilityZone":"us-east-1a","instanceType":"c3.xlarge","productDescription":"SUSE Linux","spotPrice":"0.132500","timestamp":1.403126125E9},{"availabilityZone":"us-east-1d","instanceType":"g2.2xlarge","productDescription":"Windows","spotPrice":"0.111000","timestamp":1.403126122E9},{"availabilityZone":"us-east-1d","instanceType":"g2.2xlarge","productDescription":"Windows (Amazon VPC)","spotPrice":"0.107500","timestamp":1.403126117E9},{"availabilityZone":"us-east-1a","instanceType":"g2.2xlarge","productDescription":"Windows (Amazon VPC)","spotPrice":"0.106100","timestamp":1.403126117E9},{"availabilityZone":"us-east-1b","instanceType":"r3.8xlarge","productDescription":"Linux/UNIX (Amazon VPC)","spotPrice":"0.257900","timestamp":1.403126107E9},{"availabilityZone":"us-east-1d","instanceType":"m2.4xlarge","productDescription":"Linux/UNIX (Amazon VPC)","spotPrice":"0.064200","timestamp":1.4031261E9},{"availabilityZone":"us-east-1a","instanceType":"m2.4xlarge","productDescription":"Linux/UNIX (Amazon VPC)","spotPrice":"0.064200","timestamp":1.4031261E9},{"availabilityZone":"us-east-1d","instanceType":"m2.4xlarge","productDescription":"SUSE Linux (Amazon VPC)","spotPrice":"0.148200","timestamp":1.4031261E9},{"availabilityZone":"us-east-1a","instanceType":"m2.4xlarge","productDescription":"SUSE Linux (Amazon VPC)","spotPrice":"0.148100","timestamp":1.4031261E9},{"availabilityZone":"us-east-1d","instanceType":"m3.xlarge","productDescription":"Linux/UNIX","spotPrice":"0.034600","timestamp":1.403126087E9},{"availabilityZone":"us-east-1a","instanceType":"c3.4xlarge","productDescription":"Windows (Amazon VPC)","spotPrice":"1.864100","timestamp":1.403126081E9},{"availabilityZone":"us-east-1d","instanceType":"m2.2xlarge","productDescription":"Windows (Amazon VPC)","spotPrice":"0.140100","timestamp":1.403126079E9},{"availabilityZone":"us-east-1a","instanceType":"g2.2xlarge","productDescription":"Linux/UNIX","spotPrice":"0.080300","timestamp":1.40312607E9},{"availabilityZone":"us-east-1b","instanceType":"g2.2xlarge","productDescription":"Linux/UNIX","spotPrice":"0.080300","timestamp":1.40312607E9},{"availabilityZone":"us-east-1d","instanceType":"c3.4xlarge","productDescription":"Windows","spotPrice":"0.797500","timestamp":1.403126066E9},{"availabilityZone":"us-east-1a","instanceType":"c3.4xlarge","productDescription":"Windows","spotPrice":"0.805300","timestamp":1.403126066E9},{"availabilityZone":"us-east-1a","instanceType":"c3.2xlarge","productDescription":"SUSE Linux (Amazon VPC)","spotPrice":"0.166200","timestamp":1.403126058E9},{"availabilityZone":"us-east-1d","instanceType":"m2.2xlarge","productDescription":"Windows","spotPrice":"0.140100","timestamp":1.403126057E9},{"availabilityZone":"us-east-1a","instanceType":"g2.2xlarge","productDescription":"Linux/UNIX (Amazon VPC)","spotPrice":"0.081600","timestamp":1.403126032E9},{"availabilityZone":"us-east-1a","instanceType":"g2.2xlarge","productDescription":"SUSE Linux (Amazon VPC)","spotPrice":"0.135200","timestamp":1.403126032E9},{"availabilityZone":"us-east-1b","instanceType":"g2.2xlarge","productDescription":"SUSE Linux (Amazon VPC)","spotPrice":"0.450000","timestamp":1.403126032E9},{"availabilityZone":"us-east-1d","instanceType":"m3.xlarge","productDescription":"SUSE Linux (Amazon VPC)","spotPrice":"0.083500","timestamp":1.403126024E9},{"availabilityZone":"us-east-1d","instanceType":"c1.medium","productDescription":"SUSE Linux (Amazon VPC)","spotPrice":"0.025000","timestamp":1.403126024E9},{"availabilityZone":"us-east-1a","instanceType":"m2.xlarge","productDescription":"Linux/UNIX (Amazon VPC)","spotPrice":"0.018100","timestamp":1.403126022E9},{"availabilityZone":"us-east-1b","instanceType":"r3.4xlarge","productDescription":"SUSE Linux","spotPrice":"0.231700","timestamp":1.403126017E9},{"availabilityZone":"us-east-1b","instanceType":"r3.8xlarge","productDescription":"SUSE Linux","spotPrice":"0.357700","timestamp":1.403126016E9},{"availabilityZone":"us-east-1d","instanceType":"c3.4xlarge","productDescription":"Linux/UNIX","spotPrice":"0.471900","timestamp":1.403126013E9},{"availabilityZone":"us-east-1d","instanceType":"cc2.8xlarge","productDescription":"Linux/UNIX","spotPrice":"0.269000","timestamp":1.403126008E9},{"availabilityZone":"us-east-1a","instanceType":"cc2.8xlarge","productDescription":"Linux/UNIX","spotPrice":"0.259800","timestamp":1.403126008E9},{"availabilityZone":"us-east-1b","instanceType":"cc2.8xlarge","productDescription":"Linux/UNIX","spotPrice":"0.263700","timestamp":1.403126008E9},{"availabilityZone":"us-east-1d","instanceType":"c1.medium","productDescription":"Linux/UNIX","spotPrice":"0.016300","timestamp":1.403126002E9},{"availabilityZone":"us-east-1a","instanceType":"cc2.8xlarge","productDescription":"Windows","spotPrice":"0.429000","timestamp":1.403125992E9},{"availabilityZone":"us-east-1a","instanceType":"cc2.8xlarge","productDescription":"SUSE Linux (Amazon VPC)","spotPrice":"0.267900","timestamp":1.40312599E9},{"availabilityZone":"us-east-1a","instanceType":"cc2.8xlarge","productDescription":"Linux/UNIX (Amazon VPC)","spotPrice":"0.258600","timestamp":1.403125989E9},{"availabilityZone":"us-east-1b","instanceType":"cc2.8xlarge","productDescription":"Linux/UNIX (Amazon VPC)","spotPrice":"0.264300","timestamp":1.403125989E9},{"availabilityZone":"us-east-1b","instanceType":"cg1.4xlarge","productDescription":"Linux/UNIX","spotPrice":"0.133600","timestamp":1.403125988E9},{"availabilityZone":"us-east-1d","instanceType":"c3.8xlarge","productDescription":"Windows (Amazon VPC)","spotPrice":"1.586100","timestamp":1.403125982E9},{"availabilityZone":"us-east-1a","instanceType":"c3.8xlarge","productDescription":"Windows (Amazon VPC)","spotPrice":"1.585100","timestamp":1.403125982E9},{"availabilityZone":"us-east-1d","instanceType":"m2.4xlarge","productDescription":"Linux/UNIX","spotPrice":"0.065600","timestamp":1.403125978E9},{"availabilityZone":"us-east-1a","instanceType":"m2.4xlarge","productDescription":"SUSE Linux","spotPrice":"0.148600","timestamp":1.403125977E9},{"availabilityZone":"us-east-1a","instanceType":"m2.xlarge","productDescription":"Linux/UNIX","spotPrice":"0.022800","timestamp":1.403125953E9},{"availabilityZone":"us-east-1d","instanceType":"c3.8xlarge","productDescription":"Windows","spotPrice":"1.586400","timestamp":1.403125952E9},{"availabilityZone":"us-east-1a","instanceType":"c3.8xlarge","productDescription":"Windows","spotPrice":"1.585300","timestamp":1.403125952E9},{"availabilityZone":"us-east-1b","instanceType":"m2.2xlarge","productDescription":"Linux/UNIX","spotPrice":"0.062700","timestamp":1.403125932E9},{"availabilityZone":"us-east-1a","instanceType":"c3.8xlarge","productDescription":"Linux/UNIX (Amazon VPC)","spotPrice":"0.301000","timestamp":1.403125902E9},{"availabilityZone":"us-east-1a","instanceType":"c3.8xlarge","productDescription":"SUSE Linux (Amazon VPC)","spotPrice":"0.432600","timestamp":1.403125901E9},{"availabilityZone":"us-east-1a","instanceType":"c3.2xlarge","productDescription":"Linux/UNIX","spotPrice":"0.066400","timestamp":1.403125899E9},{"availabilityZone":"us-east-1a","instanceType":"g2.2xlarge","productDescription":"Windows","spotPrice":"0.105500","timestamp":1.403125798E9},{"availabilityZone":"us-east-1b","instanceType":"g2.2xlarge","productDescription":"Windows","spotPrice":"0.106300","timestamp":1.403125798E9},{"availabilityZone":"us-east-1b","instanceType":"g2.2xlarge","productDescription":"Windows (Amazon VPC)","spotPrice":"0.136800","timestamp":1.40312579E9},{"availabilityZone":"us-east-1b","instanceType":"m2.4xlarge","productDescription":"Linux/UNIX (Amazon VPC)","spotPrice":"0.064200","timestamp":1.40312577E9},{"availabilityZone":"us-east-1b","instanceType":"m2.4xlarge","productDescription":"SUSE Linux (Amazon VPC)","spotPrice":"0.151000","timestamp":1.403125769E9},{"availabilityZone":"us-east-1d","instanceType":"m3.xlarge","productDescription":"SUSE Linux","spotPrice":"0.068900","timestamp":1.403125754E9},{"availabilityZone":"us-east-1d","instanceType":"m3.xlarge","productDescription":"Linux/UNIX (Amazon VPC)","spotPrice":"0.032100","timestamp":1.403125694E9},{"availabilityZone":"us-east-1d","instanceType":"r3.8xlarge","productDescription":"Linux/UNIX","spotPrice":"0.256500","timestamp":1.403125681E9},{"availabilityZone":"us-east-1b","instanceType":"r3.8xlarge","productDescription":"Linux/UNIX","spotPrice":"0.261400","timestamp":1.403125681E9},{"availabilityZone":"us-east-1b","instanceType":"c3.large","productDescription":"Linux/UNIX","spotPrice":"2.000000","timestamp":1.403125666E9},{"availabilityZone":"us-east-1a","instanceType":"c3.xlarge","productDescription":"SUSE Linux (Amazon VPC)","spotPrice":"0.132400","timestamp":1.403125663E9},{"availabilityZone":"us-east-1b","instanceType":"cc2.8xlarge","productDescription":"Windows","spotPrice":"0.428200","timestamp":1.403125659E9},{"availabilityZone":"us-east-1b","instanceType":"m2.4xlarge","productDescription":"Linux/UNIX","spotPrice":"0.064500","timestamp":1.403125649E9},{"availabilityZone":"us-east-1b","instanceType":"m2.4xlarge","productDescription":"SUSE Linux","spotPrice":"0.148000","timestamp":1.403125648E9},{"availabilityZone":"us-east-1d","instanceType":"m2.xlarge","productDescription":"Linux/UNIX","spotPrice":"0.016200","timestamp":1.403125622E9},{"availabilityZone":"us-east-1b","instanceType":"m2.xlarge","productDescription":"Linux/UNIX","spotPrice":"0.016100","timestamp":1.403125622E9},{"availabilityZone":"us-east-1a","instanceType":"cc1.4xlarge","productDescription":"Linux/UNIX","spotPrice":"0.128300","timestamp":1.403125615E9},{"availabilityZone":"us-east-1b","instanceType":"m1.medium","productDescription":"Linux/UNIX (Amazon VPC)","spotPrice":"0.008100","timestamp":1.403125476E9},{"availabilityZone":"us-east-1d","instanceType":"c3.8xlarge","productDescription":"Linux/UNIX","spotPrice":"2.400000","timestamp":1.403125471E9},{"availabilityZone":"us-east-1a","instanceType":"c3.8xlarge","productDescription":"Linux/UNIX","spotPrice":"2.400000","timestamp":1.403125471E9},{"availabilityZone":"us-east-1a","instanceType":"c3.8xlarge","productDescription":"SUSE Linux","spotPrice":"0.360500","timestamp":1.40312547E9},{"availabilityZone":"us-east-1d","instanceType":"g2.2xlarge","productDescription":"Linux/UNIX","spotPrice":"0.085000","timestamp":1.403125425E9},{"availabilityZone":"us-east-1a","instanceType":"c3.2xlarge","productDescription":"Linux/UNIX (Amazon VPC)","spotPrice":"0.064900","timestamp":1.403125411E9},{"availabilityZone":"us-east-1b","instanceType":"cc2.8xlarge","productDescription":"SUSE Linux","spotPrice":"0.269000","timestamp":1.403125366E9},{"availabilityZone":"us-east-1d","instanceType":"c1.medium","productDescription":"SUSE Linux","spotPrice":"0.025000","timestamp":1.403125362E9},{"availabilityZone":"us-east-1d","instanceType":"cc2.8xlarge","productDescription":"SUSE Linux (Amazon VPC)","spotPrice":"0.270800","timestamp":1.403125348E9},{"availabilityZone":"us-east-1b","instanceType":"cc2.8xlarge","productDescription":"SUSE Linux (Amazon VPC)","spotPrice":"0.266700","timestamp":1.403125348E9},{"availabilityZone":"us-east-1a","instanceType":"m2.4xlarge","productDescription":"Linux/UNIX","spotPrice":"0.064600","timestamp":1.403125345E9},{"availabilityZone":"us-east-1b","instanceType":"c1.xlarge","productDescription":"Linux/UNIX (Amazon VPC)","spotPrice":"0.064700","timestamp":1.40312525E9},{"availabilityZone":"us-east-1a","instanceType":"r3.xlarge","productDescription":"SUSE Linux","spotPrice":"0.132400","timestamp":1.40312514E9},{"availabilityZone":"us-east-1a","instanceType":"r3.8xlarge","productDescription":"Linux/UNIX (Amazon VPC)","spotPrice":"0.258000","timestamp":1.403125134E9},{"availabilityZone":"us-east-1b","instanceType":"m3.xlarge","productDescription":"Linux/UNIX (Amazon VPC)","spotPrice":"2.500000","timestamp":1.40312505E9},{"availabilityZone":"us-east-1a","instanceType":"r3.xlarge","productDescription":"SUSE Linux (Amazon VPC)","spotPrice":"0.132400","timestamp":1.403125039E9},{"availabilityZone":"us-east-1b","instanceType":"hi1.4xlarge","productDescription":"Linux/UNIX","spotPrice":"0.130400","timestamp":1.403124985E9},{"availabilityZone":"us-east-1a","instanceType":"c3.4xlarge","productDescription":"SUSE Linux (Amazon VPC)","spotPrice":"1.300100","timestamp":1.40312494E9},{"availabilityZone":"us-east-1a","instanceType":"c1.xlarge","productDescription":"SUSE Linux (Amazon VPC)","spotPrice":"0.084500","timestamp":1.403124928E9},{"availabilityZone":"us-east-1a","instanceType":"c1.xlarge","productDescription":"Linux/UNIX (Amazon VPC)","spotPrice":"0.064500","timestamp":1.403124927E9},{"availabilityZone":"us-east-1b","instanceType":"hi1.4xlarge","productDescription":"SUSE Linux (Amazon VPC)","spotPrice":"0.235500","timestamp":1.40312484E9},{"availabilityZone":"us-east-1a","instanceType":"hi1.4xlarge","productDescription":"Linux/UNIX (Amazon VPC)","spotPrice":"0.129100","timestamp":1.40312484E9},{"availabilityZone":"us-east-1d","instanceType":"c3.2xlarge","productDescription":"SUSE Linux (Amazon VPC)","spotPrice":"0.164700","timestamp":1.403124769E9},{"availabilityZone":"us-east-1d","instanceType":"g2.2xlarge","productDescription":"SUSE Linux (Amazon VPC)","spotPrice":"0.131600","timestamp":1.403124749E9},{"availabilityZone":"us-east-1a","instanceType":"r3.4xlarge","productDescription":"SUSE Linux (Amazon VPC)","spotPrice":"0.242000","timestamp":1.403124746E9},{"availabilityZone":"us-east-1a","instanceType":"c3.4xlarge","productDescription":"Linux/UNIX","spotPrice":"12.000000","timestamp":1.403124732E9},{"availabilityZone":"us-east-1a","instanceType":"cc2.8xlarge","productDescription":"SUSE Linux","spotPrice":"0.262800","timestamp":1.40312473E9},{"availabilityZone":"us-east-1d","instanceType":"c3.xlarge","productDescription":"Linux/UNIX (Amazon VPC)","spotPrice":"0.032400","timestamp":1.403124715E9},{"availabilityZone":"us-east-1b","instanceType":"m2.2xlarge","productDescription":"Linux/UNIX (Amazon VPC)","spotPrice":"0.032600","timestamp":1.40312471E9},{"availabilityZone":"us-east-1d","instanceType":"m2.4xlarge","productDescription":"SUSE Linux","spotPrice":"0.147300","timestamp":1.4031247E9},{"availabilityZone":"us-east-1a","instanceType":"m2.xlarge","productDescription":"Windows","spotPrice":"0.070200","timestamp":1.40312468E9},{"availabilityZone":"us-east-1d","instanceType":"hi1.4xlarge","productDescription":"Linux/UNIX","spotPrice":"0.129000","timestamp":1.403124676E9},{"availabilityZone":"us-east-1a","instanceType":"hi1.4xlarge","productDescription":"SUSE Linux","spotPrice":"0.237200","timestamp":1.403124675E9},{"availabilityZone":"us-east-1a","instanceType":"m2.xlarge","productDescription":"SUSE Linux","spotPrice":"0.269800","timestamp":1.403124669E9},{"availabilityZone":"us-east-1a","instanceType":"c3.xlarge","productDescription":"Linux/UNIX","spotPrice":"0.032200","timestamp":1.40312452E9},{"availabilityZone":"us-east-1b","instanceType":"c3.8xlarge","productDescription":"Linux/UNIX","spotPrice":"2.400000","timestamp":1.40312451E9},{"availabilityZone":"us-east-1b","instanceType":"m3.medium","productDescription":"Linux/UNIX","spotPrice":"0.452000","timestamp":1.403124487E9},{"availabilityZone":"us-east-1d","instanceType":"m1.xlarge","productDescription":"Linux/UNIX","spotPrice":"0.032100","timestamp":1.403124479E9},{"availabilityZone":"us-east-1d","instanceType":"m1.medium","productDescription":"Linux/UNIX","spotPrice":"0.008100","timestamp":1.403124478E9},{"availabilityZone":"us-east-1a","instanceType":"t1.micro","productDescription":"SUSE Linux (Amazon VPC)","spotPrice":"0.006100","timestamp":1.403124459E9},{"availabilityZone":"us-east-1d","instanceType":"c3.xlarge","productDescription":"Windows (Amazon VPC)","spotPrice":"0.198100","timestamp":1.403124212E9},{"availabilityZone":"us-east-1b","instanceType":"r3.xlarge","productDescription":"SUSE Linux","spotPrice":"0.132500","timestamp":1.40312421E9},{"availabilityZone":"us-east-1d","instanceType":"hi1.4xlarge","productDescription":"SUSE Linux (Amazon VPC)","spotPrice":"0.257800","timestamp":1.403123906E9},{"availabilityZone":"us-east-1d","instanceType":"c3.8xlarge","productDescription":"SUSE Linux","spotPrice":"0.377500","timestamp":1.40312389E9},{"availabilityZone":"us-east-1a","instanceType":"cg1.4xlarge","productDescription":"Linux/UNIX (Amazon VPC)","spotPrice":"2.100100","timestamp":1.403123874E9},{"availabilityZone":"us-east-1a","instanceType":"m2.xlarge","productDescription":"SUSE Linux (Amazon VPC)","spotPrice":"0.051200","timestamp":1.403123811E9},{"availabilityZone":"us-east-1b","instanceType":"r3.4xlarge","productDescription":"Linux/UNIX","spotPrice":"0.130500","timestamp":1.403123808E9},{"availabilityZone":"us-east-1b","instanceType":"c3.2xlarge","productDescription":"Linux/UNIX","spotPrice":"2.000000","timestamp":1.4031237E9},{"availabilityZone":"us-east-1a","instanceType":"r3.8xlarge","productDescription":"SUSE Linux (Amazon VPC)","spotPrice":"0.361900","timestamp":1.403123587E9},{"availabilityZone":"us-east-1d","instanceType":"c3.2xlarge","productDescription":"Linux/UNIX (Amazon VPC)","spotPrice":"0.064300","timestamp":1.403123536E9},{"availabilityZone":"us-east-1a","instanceType":"c1.medium","productDescription":"SUSE Linux (Amazon VPC)","spotPrice":"0.024200","timestamp":1.4031235E9},{"availabilityZone":"us-east-1b","instanceType":"m2.xlarge","productDescription":"SUSE Linux (Amazon VPC)","spotPrice":"0.042400","timestamp":1.403123497E9},{"availabilityZone":"us-east-1d","instanceType":"m1.small","productDescription":"Linux/UNIX","spotPrice":"0.007100","timestamp":1.403123425E9},{"availabilityZone":"us-east-1b","instanceType":"m3.2xlarge","productDescription":"Windows","spotPrice":"0.557300","timestamp":1.403123386E9},{"availabilityZone":"us-east-1b","instanceType":"m3.2xlarge","productDescription":"Windows (Amazon VPC)","spotPrice":"0.557300","timestamp":1.403123291E9},{"availabilityZone":"us-east-1d","instanceType":"m2.xlarge","productDescription":"SUSE Linux (Amazon VPC)","spotPrice":"0.042400","timestamp":1.403123189E9},{"availabilityZone":"us-east-1b","instanceType":"m2.2xlarge","productDescription":"SUSE Linux (Amazon VPC)","spotPrice":"0.090200","timestamp":1.403123163E9},{"availabilityZone":"us-east-1d","instanceType":"c1.xlarge","productDescription":"Linux/UNIX","spotPrice":"0.064100","timestamp":1.403122885E9},{"availabilityZone":"us-east-1d","instanceType":"m3.2xlarge","productDescription":"Windows","spotPrice":"0.275500","timestamp":1.403122766E9},{"availabilityZone":"us-east-1b","instanceType":"cr1.8xlarge","productDescription":"Linux/UNIX (Amazon VPC)","spotPrice":"0.274500","timestamp":1.40312251E9},{"availabilityZone":"us-east-1b","instanceType":"m2.2xlarge","productDescription":"SUSE Linux","spotPrice":"0.084000","timestamp":1.403122477E9},{"availabilityZone":"us-east-1b","instanceType":"cr1.8xlarge","productDescription":"Linux/UNIX","spotPrice":"0.326600","timestamp":1.403122445E9},{"availabilityZone":"us-east-1b","instanceType":"hi1.4xlarge","productDescription":"Linux/UNIX (Amazon VPC)","spotPrice":"0.128200","timestamp":1.403122356E9},{"availabilityZone":"us-east-1d","instanceType":"c3.xlarge","productDescription":"Linux/UNIX","spotPrice":"0.032200","timestamp":1.403122353E9},{"availabilityZone":"us-east-1a","instanceType":"m2.2xlarge","productDescription":"Windows","spotPrice":"0.140200","timestamp":1.403122284E9},{"availabilityZone":"us-east-1d","instanceType":"r3.2xlarge","productDescription":"SUSE Linux (Amazon VPC)","spotPrice":"0.164700","timestamp":1.403122279E9},{"availabilityZone":"us-east-1d","instanceType":"cc2.8xlarge","productDescription":"SUSE Linux","spotPrice":"0.297000","timestamp":1.403122235E9},{"availabilityZone":"us-east-1a","instanceType":"r3.4xlarge","productDescription":"SUSE Linux","spotPrice":"0.242000","timestamp":1.403121909E9},{"availabilityZone":"us-east-1b","instanceType":"c1.xlarge","productDescription":"Windows","spotPrice":"0.200100","timestamp":1.403121907E9},{"availabilityZone":"us-east-1a","instanceType":"cr1.8xlarge","productDescription":"SUSE Linux","spotPrice":"0.481000","timestamp":1.403121804E9},{"availabilityZone":"us-east-1b","instanceType":"c1.xlarge","productDescription":"Windows (Amazon VPC)","spotPrice":"0.200100","timestamp":1.403121717E9},{"availabilityZone":"us-east-1a","instanceType":"hi1.4xlarge","productDescription":"Linux/UNIX","spotPrice":"0.129600","timestamp":1.403121503E9},{"availabilityZone":"us-east-1a","instanceType":"hi1.4xlarge","productDescription":"SUSE Linux (Amazon VPC)","spotPrice":"0.237200","timestamp":1.403121359E9},{"availabilityZone":"us-east-1d","instanceType":"c3.4xlarge","productDescription":"Linux/UNIX (Amazon VPC)","spotPrice":"1.680000","timestamp":1.403121154E9},{"availabilityZone":"us-east-1a","instanceType":"m1.medium","productDescription":"Linux/UNIX (Amazon VPC)","spotPrice":"0.008100","timestamp":1.403121044E9},{"availabilityZone":"us-east-1b","instanceType":"m1.xlarge","productDescription":"SUSE Linux","spotPrice":"0.057100","timestamp":1.403120702E9},{"availabilityZone":"us-east-1d","instanceType":"c1.medium","productDescription":"Linux/UNIX (Amazon VPC)","spotPrice":"0.016100","timestamp":1.403120641E9},{"availabilityZone":"us-east-1b","instanceType":"r3.8xlarge","productDescription":"SUSE Linux (Amazon VPC)","spotPrice":"0.364500","timestamp":1.403120415E9},{"availabilityZone":"us-east-1d","instanceType":"c3.large","productDescription":"Linux/UNIX","spotPrice":"0.016100","timestamp":1.403120318E9},{"availabilityZone":"us-east-1a","instanceType":"m3.large","productDescription":"Windows (Amazon VPC)","spotPrice":"0.117100","timestamp":1.403120077E9},{"availabilityZone":"us-east-1a","instanceType":"m2.2xlarge","productDescription":"Linux/UNIX (Amazon VPC)","spotPrice":"1.640000","timestamp":1.403120006E9},{"availabilityZone":"us-east-1d","instanceType":"m3.2xlarge","productDescription":"Linux/UNIX (Amazon VPC)","spotPrice":"0.064100","timestamp":1.403119819E9},{"availabilityZone":"us-east-1a","instanceType":"m3.medium","productDescription":"Windows","spotPrice":"0.176000","timestamp":1.403119789E9},{"availabilityZone":"us-east-1b","instanceType":"g2.2xlarge","productDescription":"Linux/UNIX (Amazon VPC)","spotPrice":"0.080000","timestamp":1.403119724E9},{"availabilityZone":"us-east-1a","instanceType":"m1.large","productDescription":"Linux/UNIX (Amazon VPC)","spotPrice":"0.016100","timestamp":1.403119636E9},{"availabilityZone":"us-east-1b","instanceType":"c1.xlarge","productDescription":"Linux/UNIX","spotPrice":"0.064100","timestamp":1.40311943E9},{"availabilityZone":"us-east-1b","instanceType":"m1.large","productDescription":"SUSE Linux (Amazon VPC)","spotPrice":"0.032300","timestamp":1.403119334E9},{"availabilityZone":"us-east-1d","instanceType":"m3.large","productDescription":"SUSE Linux","spotPrice":"0.116100","timestamp":1.403119216E9},{"availabilityZone":"us-east-1d","instanceType":"m3.xlarge","productDescription":"Windows (Amazon VPC)","spotPrice":"0.138100","timestamp":1.403119153E9},{"availabilityZone":"us-east-1b","instanceType":"cg1.4xlarge","productDescription":"SUSE Linux","spotPrice":"0.282800","timestamp":1.403119081E9},{"availabilityZone":"us-east-1a","instanceType":"g2.2xlarge","productDescription":"SUSE Linux","spotPrice":"0.700000","timestamp":1.403118831E9},{"availabilityZone":"us-east-1b","instanceType":"r3.2xlarge","productDescription":"Linux/UNIX (Amazon VPC)","spotPrice":"0.064100","timestamp":1.403118807E9},{"availabilityZone":"us-east-1d","instanceType":"m2.xlarge","productDescription":"Linux/UNIX (Amazon VPC)","spotPrice":"0.016100","timestamp":1.403118781E9},{"availabilityZone":"us-east-1b","instanceType":"c3.4xlarge","productDescription":"Linux/UNIX","spotPrice":"1.200100","timestamp":1.403118774E9},{"availabilityZone":"us-east-1b","instanceType":"m2.4xlarge","productDescription":"Windows","spotPrice":"0.280200","timestamp":1.40311872E9},{"availabilityZone":"us-east-1d","instanceType":"r3.8xlarge","productDescription":"SUSE Linux (Amazon VPC)","spotPrice":"0.358200","timestamp":1.40311856E9},{"availabilityZone":"us-east-1d","instanceType":"r3.8xlarge","productDescription":"SUSE Linux","spotPrice":"0.358000","timestamp":1.403118473E9},{"availabilityZone":"us-east-1a","instanceType":"c3.large","productDescription":"Linux/UNIX","spotPrice":"0.016200","timestamp":1.40311846E9},{"availabilityZone":"us-east-1b","instanceType":"m3.2xlarge","productDescription":"Linux/UNIX","spotPrice":"1.000000","timestamp":1.403118282E9},{"availabilityZone":"us-east-1d","instanceType":"r3.8xlarge","productDescription":"Linux/UNIX (Amazon VPC)","spotPrice":"0.256300","timestamp":1.403118256E9},{"availabilityZone":"us-east-1a","instanceType":"r3.2xlarge","productDescription":"SUSE Linux (Amazon VPC)","spotPrice":"0.164700","timestamp":1.403118197E9},{"availabilityZone":"us-east-1d","instanceType":"m2.2xlarge","productDescription":"Linux/UNIX","spotPrice":"0.394000","timestamp":1.403118069E9},{"availabilityZone":"us-east-1d","instanceType":"m3.large","productDescription":"SUSE Linux (Amazon VPC)","spotPrice":"0.116100","timestamp":1.403117576E9},{"availabilityZone":"us-east-1a","instanceType":"c3.2xlarge","productDescription":"Windows","spotPrice":"0.396100","timestamp":1.403117557E9},{"availabilityZone":"us-east-1b","instanceType":"cc1.4xlarge","productDescription":"SUSE Linux","spotPrice":"0.247100","timestamp":1.403117451E9},{"availabilityZone":"us-east-1a","instanceType":"m1.large","productDescription":"SUSE Linux (Amazon VPC)","spotPrice":"0.032100","timestamp":1.403117439E9},{"availabilityZone":"us-east-1b","instanceType":"c3.2xlarge","productDescription":"SUSE Linux","spotPrice":"0.700000","timestamp":1.403117409E9},{"availabilityZone":"us-east-1d","instanceType":"m3.large","productDescription":"Linux/UNIX","spotPrice":"0.016100","timestamp":1.403117318E9},{"availabilityZone":"us-east-1a","instanceType":"r3.2xlarge","productDescription":"Windows (Amazon VPC)","spotPrice":"0.444100","timestamp":1.40311729E9},{"availabilityZone":"us-east-1a","instanceType":"m2.2xlarge","productDescription":"SUSE Linux (Amazon VPC)","spotPrice":"0.920100","timestamp":1.403117177E9},{"availabilityZone":"us-east-1b","instanceType":"m3.medium","productDescription":"Windows","spotPrice":"0.200000","timestamp":1.403116963E9},{"availabilityZone":"us-east-1d","instanceType":"m3.large","productDescription":"Linux/UNIX (Amazon VPC)","spotPrice":"0.016100","timestamp":1.403116948E9},{"availabilityZone":"us-east-1d","instanceType":"c3.4xlarge","productDescription":"SUSE Linux","spotPrice":"0.347200","timestamp":1.403116861E9},{"availabilityZone":"us-east-1b","instanceType":"c3.8xlarge","productDescription":"SUSE Linux (Amazon VPC)","spotPrice":"2.500000","timestamp":1.403116734E9},{"availabilityZone":"us-east-1d","instanceType":"m3.medium","productDescription":"Windows","spotPrice":"0.059100","timestamp":1.403116604E9},{"availabilityZone":"us-east-1d","instanceType":"m3.medium","productDescription":"Linux/UNIX","spotPrice":"0.008100","timestamp":1.403116594E9},{"availabilityZone":"us-east-1d","instanceType":"m3.medium","productDescription":"SUSE Linux","spotPrice":"0.108100","timestamp":1.403116594E9},{"availabilityZone":"us-east-1a","instanceType":"m3.medium","productDescription":"SUSE Linux","spotPrice":"0.213000","timestamp":1.403116593E9},{"availabilityZone":"us-east-1a","instanceType":"m3.large","productDescription":"SUSE Linux (Amazon VPC)","spotPrice":"0.143000","timestamp":1.403116589E9},{"availabilityZone":"us-east-1b","instanceType":"m3.large","productDescription":"SUSE Linux (Amazon VPC)","spotPrice":"0.143000","timestamp":1.403116589E9},{"availabilityZone":"us-east-1d","instanceType":"r3.xlarge","productDescription":"SUSE Linux (Amazon VPC)","spotPrice":"0.132400","timestamp":1.403116512E9},{"availabilityZone":"us-east-1a","instanceType":"m3.medium","productDescription":"SUSE Linux (Amazon VPC)","spotPrice":"0.213000","timestamp":1.403116401E9},{"availabilityZone":"us-east-1b","instanceType":"m3.medium","productDescription":"SUSE Linux (Amazon VPC)","spotPrice":"0.213000","timestamp":1.403116401E9},{"availabilityZone":"us-east-1b","instanceType":"m3.medium","productDescription":"Linux/UNIX (Amazon VPC)","spotPrice":"0.452000","timestamp":1.4031164E9},{"availabilityZone":"us-east-1a","instanceType":"c1.xlarge","productDescription":"Windows (Amazon VPC)","spotPrice":"0.200100","timestamp":1.403116289E9},{"availabilityZone":"us-east-1a","instanceType":"m3.2xlarge","productDescription":"Linux/UNIX","spotPrice":"1.000000","timestamp":1.403116284E9},{"availabilityZone":"us-east-1a","instanceType":"m3.2xlarge","productDescription":"SUSE Linux","spotPrice":"1.000000","timestamp":1.403116284E9},{"availabilityZone":"us-east-1b","instanceType":"m3.2xlarge","productDescription":"SUSE Linux","spotPrice":"1.000000","timestamp":1.403116284E9},{"availabilityZone":"us-east-1a","instanceType":"m3.large","productDescription":"Linux/UNIX","spotPrice":"0.896000","timestamp":1.403116279E9},{"availabilityZone":"us-east-1a","instanceType":"m3.2xlarge","productDescription":"Linux/UNIX (Amazon VPC)","spotPrice":"2.000000","timestamp":1.403116279E9},{"availabilityZone":"us-east-1b","instanceType":"m3.2xlarge","productDescription":"Linux/UNIX (Amazon VPC)","spotPrice":"2.000000","timestamp":1.403116279E9},{"availabilityZone":"us-east-1a","instanceType":"m3.large","productDescription":"SUSE Linux","spotPrice":"0.143000","timestamp":1.403116278E9},{"availabilityZone":"us-east-1b","instanceType":"m3.large","productDescription":"SUSE Linux","spotPrice":"0.143000","timestamp":1.403116278E9},{"availabilityZone":"us-east-1a","instanceType":"m3.2xlarge","productDescription":"SUSE Linux (Amazon VPC)","spotPrice":"1.000000","timestamp":1.403116278E9},{"availabilityZone":"us-east-1b","instanceType":"m3.2xlarge","productDescription":"SUSE Linux (Amazon VPC)","spotPrice":"1.000000","timestamp":1.403116278E9},{"availabilityZone":"us-east-1a","instanceType":"m3.xlarge","productDescription":"SUSE Linux (Amazon VPC)","spotPrice":"0.550100","timestamp":1.403116189E9},{"availabilityZone":"us-east-1b","instanceType":"m3.xlarge","productDescription":"SUSE Linux (Amazon VPC)","spotPrice":"0.550100","timestamp":1.403116189E9},{"availabilityZone":"us-east-1a","instanceType":"cc1.4xlarge","productDescription":"SUSE Linux","spotPrice":"0.220800","timestamp":1.403116095E9},{"availabilityZone":"us-east-1a","instanceType":"m2.2xlarge","productDescription":"Linux/UNIX","spotPrice":"3.000000","timestamp":1.40311608E9},{"availabilityZone":"us-east-1a","instanceType":"m3.medium","productDescription":"Windows (Amazon VPC)","spotPrice":"0.176000","timestamp":1.40311592E9},{"availabilityZone":"us-east-1b","instanceType":"m3.medium","productDescription":"SUSE Linux","spotPrice":"0.213000","timestamp":1.403115912E9},{"availabilityZone":"us-east-1b","instanceType":"m1.small","productDescription":"Linux/UNIX (Amazon VPC)","spotPrice":"0.500000","timestamp":1.403115893E9},{"availabilityZone":"us-east-1d","instanceType":"cr1.8xlarge","productDescription":"Linux/UNIX (Amazon VPC)","spotPrice":"0.580500","timestamp":1.403115797E9},{"availabilityZone":"us-east-1b","instanceType":"m2.xlarge","productDescription":"SUSE Linux","spotPrice":"0.042300","timestamp":1.403115788E9},{"availabilityZone":"us-east-1a","instanceType":"m2.2xlarge","productDescription":"SUSE Linux","spotPrice":"0.920100","timestamp":1.403115766E9},{"availabilityZone":"us-east-1d","instanceType":"c3.4xlarge","productDescription":"Windows (Amazon VPC)","spotPrice":"1.864100","timestamp":1.403115591E9},{"availabilityZone":"us-east-1d","instanceType":"r3.2xlarge","productDescription":"SUSE Linux","spotPrice":"0.164700","timestamp":1.403115297E9},{"availabilityZone":"us-east-1a","instanceType":"m1.small","productDescription":"SUSE Linux (Amazon VPC)","spotPrice":"0.013100","timestamp":1.403115265E9},{"availabilityZone":"us-east-1d","instanceType":"m3.large","productDescription":"Windows","spotPrice":"0.117100","timestamp":1.403115215E9},{"availabilityZone":"us-east-1a","instanceType":"m1.medium","productDescription":"SUSE Linux","spotPrice":"0.019100","timestamp":1.403114957E9},{"availabilityZone":"us-east-1b","instanceType":"hi1.4xlarge","productDescription":"Windows (Amazon VPC)","spotPrice":"0.481100","timestamp":1.403114877E9},{"availabilityZone":"us-east-1b","instanceType":"m2.2xlarge","productDescription":"Windows","spotPrice":"0.140100","timestamp":1.403114597E9},{"availabilityZone":"us-east-1a","instanceType":"m1.small","productDescription":"Linux/UNIX","spotPrice":"0.007100","timestamp":1.403114496E9},{"availabilityZone":"us-east-1b","instanceType":"g2.2xlarge","productDescription":"SUSE Linux","spotPrice":"0.750000","timestamp":1.403114281E9},{"availabilityZone":"us-east-1a","instanceType":"r3.8xlarge","productDescription":"Linux/UNIX","spotPrice":"0.257200","timestamp":1.403114225E9},{"availabilityZone":"us-east-1d","instanceType":"cc2.8xlarge","productDescription":"Windows","spotPrice":"0.428300","timestamp":1.403113887E9},{"availabilityZone":"us-east-1d","instanceType":"m2.4xlarge","productDescription":"Windows (Amazon VPC)","spotPrice":"0.280100","timestamp":1.403113881E9},{"availabilityZone":"us-east-1b","instanceType":"m1.xlarge","productDescription":"Linux/UNIX","spotPrice":"0.032100","timestamp":1.403113316E9},{"availabilityZone":"us-east-1b","instanceType":"m3.xlarge","productDescription":"Windows","spotPrice":"0.702000","timestamp":1.403113056E9},{"availabilityZone":"us-east-1d","instanceType":"c3.large","productDescription":"Windows","spotPrice":"0.104100","timestamp":1.40311303E9},{"availabilityZone":"us-east-1d","instanceType":"c3.large","productDescription":"SUSE Linux (Amazon VPC)","spotPrice":"0.116100","timestamp":1.403112698E9},{"availabilityZone":"us-east-1b","instanceType":"c3.2xlarge","productDescription":"Windows","spotPrice":"0.610500","timestamp":1.403112636E9},{"availabilityZone":"us-east-1a","instanceType":"m2.2xlarge","productDescription":"Windows (Amazon VPC)","spotPrice":"0.140100","timestamp":1.403112338E9},{"availabilityZone":"us-east-1d","instanceType":"c3.8xlarge","productDescription":"SUSE Linux (Amazon VPC)","spotPrice":"2.500000","timestamp":1.403112167E9},{"availabilityZone":"us-east-1b","instanceType":"m2.2xlarge","productDescription":"Windows (Amazon VPC)","spotPrice":"0.140100","timestamp":1.403111715E9},{"availabilityZone":"us-east-1d","instanceType":"cc2.8xlarge","productDescription":"Linux/UNIX (Amazon VPC)","spotPrice":"0.265000","timestamp":1.40311068E9},{"availabilityZone":"us-east-1b","instanceType":"t1.micro","productDescription":"SUSE Linux (Amazon VPC)","spotPrice":"0.006100","timestamp":1.403110441E9},{"availabilityZone":"us-east-1b","instanceType":"t1.micro","productDescription":"Linux/UNIX (Amazon VPC)","spotPrice":"0.003100","timestamp":1.403110132E9},{"availabilityZone":"us-east-1d","instanceType":"m2.4xlarge","productDescription":"Windows","spotPrice":"0.280100","timestamp":1.403110034E9},{"availabilityZone":"us-east-1d","instanceType":"g2.2xlarge","productDescription":"SUSE Linux","spotPrice":"0.700000","timestamp":1.403109511E9},{"availabilityZone":"us-east-1d","instanceType":"m1.small","productDescription":"SUSE Linux (Amazon VPC)","spotPrice":"0.013100","timestamp":1.403109182E9},{"availabilityZone":"us-east-1d","instanceType":"r3.4xlarge","productDescription":"Linux/UNIX","spotPrice":"0.128300","timestamp":1.403109135E9},{"availabilityZone":"us-east-1d","instanceType":"r3.4xlarge","productDescription":"SUSE Linux","spotPrice":"0.240200","timestamp":1.403109135E9},{"availabilityZone":"us-east-1d","instanceType":"r3.4xlarge","productDescription":"Linux/UNIX (Amazon VPC)","spotPrice":"0.128100","timestamp":1.403108846E9},{"availabilityZone":"us-east-1d","instanceType":"r3.4xlarge","productDescription":"SUSE Linux (Amazon VPC)","spotPrice":"0.240200","timestamp":1.403108846E9},{"availabilityZone":"us-east-1b","instanceType":"c3.8xlarge","productDescription":"Windows (Amazon VPC)","spotPrice":"1.669800","timestamp":1.403108506E9},{"availabilityZone":"us-east-1b","instanceType":"r3.large","productDescription":"SUSE Linux","spotPrice":"0.116100","timestamp":1.403108142E9},{"availabilityZone":"us-east-1b","instanceType":"m1.xlarge","productDescription":"SUSE Linux (Amazon VPC)","spotPrice":"0.057100","timestamp":1.403107911E9},{"availabilityZone":"us-east-1b","instanceType":"m3.xlarge","productDescription":"Windows (Amazon VPC)","spotPrice":"2.800000","timestamp":1.403107643E9},{"availabilityZone":"us-east-1a","instanceType":"c1.xlarge","productDescription":"Linux/UNIX","spotPrice":"0.064100","timestamp":1.40310761E9},{"availabilityZone":"us-east-1b","instanceType":"c1.medium","productDescription":"SUSE Linux (Amazon VPC)","spotPrice":"0.024100","timestamp":1.4031076E9},{"availabilityZone":"us-east-1b","instanceType":"r3.large","productDescription":"SUSE Linux (Amazon VPC)","spotPrice":"0.116100","timestamp":1.403107405E9},{"availabilityZone":"us-east-1b","instanceType":"m3.xlarge","productDescription":"Linux/UNIX","spotPrice":"1.750000","timestamp":1.403107361E9},{"availabilityZone":"us-east-1b","instanceType":"m1.large","productDescription":"Linux/UNIX (Amazon VPC)","spotPrice":"0.016100","timestamp":1.403107224E9},{"availabilityZone":"us-east-1a","instanceType":"m1.large","productDescription":"Linux/UNIX","spotPrice":"0.016100","timestamp":1.403107073E9},{"availabilityZone":"us-east-1b","instanceType":"c3.xlarge","productDescription":"SUSE Linux (Amazon VPC)","spotPrice":"0.400100","timestamp":1.403106978E9},{"availabilityZone":"us-east-1b","instanceType":"c3.8xlarge","productDescription":"Windows","spotPrice":"1.669800","timestamp":1.403106938E9},{"availabilityZone":"us-east-1a","instanceType":"m3.2xlarge","productDescription":"Windows","spotPrice":"0.557300","timestamp":1.403106908E9},{"availabilityZone":"us-east-1a","instanceType":"t1.micro","productDescription":"Linux/UNIX","spotPrice":"0.003100","timestamp":1.403106404E9},{"availabilityZone":"us-east-1b","instanceType":"t1.micro","productDescription":"Linux/UNIX","spotPrice":"0.003100","timestamp":1.403106403E9},{"availabilityZone":"us-east-1b","instanceType":"c1.medium","productDescription":"Linux/UNIX (Amazon VPC)","spotPrice":"0.016100","timestamp":1.403106368E9},{"availabilityZone":"us-east-1b","instanceType":"c1.medium","productDescription":"SUSE Linux","spotPrice":"0.024100","timestamp":1.403106345E9},{"availabilityZone":"us-east-1d","instanceType":"c3.xlarge","productDescription":"SUSE Linux (Amazon VPC)","spotPrice":"0.132400","timestamp":1.403105996E9},{"availabilityZone":"us-east-1d","instanceType":"t1.micro","productDescription":"SUSE Linux","spotPrice":"0.006100","timestamp":1.403105912E9},{"availabilityZone":"us-east-1b","instanceType":"m2.xlarge","productDescription":"Windows (Amazon VPC)","spotPrice":"0.070100","timestamp":1.403105786E9},{"availabilityZone":"us-east-1b","instanceType":"c1.medium","productDescription":"Linux/UNIX","spotPrice":"0.016100","timestamp":1.403105666E9},{"availabilityZone":"us-east-1b","instanceType":"m2.xlarge","productDescription":"Windows","spotPrice":"0.070100","timestamp":1.403105632E9},{"availabilityZone":"us-east-1a","instanceType":"c1.medium","productDescription":"Linux/UNIX (Amazon VPC)","spotPrice":"0.016100","timestamp":1.403105366E9},{"availabilityZone":"us-east-1a","instanceType":"c1.medium","productDescription":"Linux/UNIX","spotPrice":"0.016100","timestamp":1.403105348E9},{"availabilityZone":"us-east-1a","instanceType":"c1.medium","productDescription":"Windows (Amazon VPC)","spotPrice":"0.050100","timestamp":1.403105289E9},{"availabilityZone":"us-east-1b","instanceType":"c1.medium","productDescription":"Windows","spotPrice":"0.050100","timestamp":1.403105245E9},{"availabilityZone":"us-east-1d","instanceType":"m1.large","productDescription":"Linux/UNIX","spotPrice":"0.016100","timestamp":1.403105125E9},{"availabilityZone":"us-east-1b","instanceType":"m1.large","productDescription":"Linux/UNIX","spotPrice":"0.016100","timestamp":1.403104801E9},{"availabilityZone":"us-east-1b","instanceType":"r3.2xlarge","productDescription":"SUSE Linux","spotPrice":"0.164500","timestamp":1.403104792E9},{"availabilityZone":"us-east-1d","instanceType":"t1.micro","productDescription":"Linux/UNIX (Amazon VPC)","spotPrice":"0.003100","timestamp":1.403104752E9},{"availabilityZone":"us-east-1a","instanceType":"t1.micro","productDescription":"Linux/UNIX (Amazon VPC)","spotPrice":"0.003100","timestamp":1.403104752E9},{"availabilityZone":"us-east-1a","instanceType":"c1.medium","productDescription":"Windows","spotPrice":"0.050100","timestamp":1.403104605E9},{"availabilityZone":"us-east-1d","instanceType":"m1.large","productDescription":"SUSE Linux","spotPrice":"0.032100","timestamp":1.403102913E9},{"availabilityZone":"us-east-1b","instanceType":"r3.4xlarge","productDescription":"SUSE Linux (Amazon VPC)","spotPrice":"0.240200","timestamp":1.403102831E9},{"availabilityZone":"us-east-1b","instanceType":"c3.large","productDescription":"Linux/UNIX (Amazon VPC)","spotPrice":"0.580000","timestamp":1.403101998E9},{"availabilityZone":"us-east-1d","instanceType":"c3.2xlarge","productDescription":"SUSE Linux","spotPrice":"0.164200","timestamp":1.403101785E9},{"availabilityZone":"us-east-1d","instanceType":"m2.xlarge","productDescription":"Windows","spotPrice":"0.070100","timestamp":1.403101529E9},{"availabilityZone":"us-east-1b","instanceType":"r3.4xlarge","productDescription":"Windows","spotPrice":"0.672100","timestamp":1.403101264E9},{"availabilityZone":"us-east-1b","instanceType":"c3.2xlarge","productDescription":"SUSE Linux (Amazon VPC)","spotPrice":"0.700000","timestamp":1.403100987E9},{"availabilityZone":"us-east-1a","instanceType":"c3.4xlarge","productDescription":"SUSE Linux","spotPrice":"1.300100","timestamp":1.403100282E9},{"availabilityZone":"us-east-1d","instanceType":"c3.2xlarge","productDescription":"Windows (Amazon VPC)","spotPrice":"0.396100","timestamp":1.40309916E9},{"availabilityZone":"us-east-1d","instanceType":"c3.2xlarge","productDescription":"Windows","spotPrice":"0.396100","timestamp":1.4030991E9},{"availabilityZone":"us-east-1d","instanceType":"c3.xlarge","productDescription":"SUSE Linux","spotPrice":"0.132300","timestamp":1.403098865E9},{"availabilityZone":"us-east-1b","instanceType":"m3.large","productDescription":"Linux/UNIX (Amazon VPC)","spotPrice":"0.896000","timestamp":1.403098515E9},{"availabilityZone":"us-east-1d","instanceType":"m2.2xlarge","productDescription":"Linux/UNIX (Amazon VPC)","spotPrice":"1.640000","timestamp":1.403098432E9},{"availabilityZone":"us-east-1d","instanceType":"c1.medium","productDescription":"Windows","spotPrice":"0.050100","timestamp":1.403098331E9},{"availabilityZone":"us-east-1a","instanceType":"r3.2xlarge","productDescription":"SUSE Linux","spotPrice":"0.164600","timestamp":1.403096928E9},{"availabilityZone":"us-east-1d","instanceType":"r3.xlarge","productDescription":"SUSE Linux","spotPrice":"0.132400","timestamp":1.403096033E9},{"availabilityZone":"us-east-1d","instanceType":"c3.4xlarge","productDescription":"SUSE Linux (Amazon VPC)","spotPrice":"1.300100","timestamp":1.403095541E9},{"availabilityZone":"us-east-1b","instanceType":"c3.xlarge","productDescription":"SUSE Linux","spotPrice":"0.400100","timestamp":1.403094527E9},{"availabilityZone":"us-east-1d","instanceType":"r3.large","productDescription":"SUSE Linux","spotPrice":"0.116100","timestamp":1.403094067E9},{"availabilityZone":"us-east-1b","instanceType":"m1.small","productDescription":"SUSE Linux (Amazon VPC)","spotPrice":"0.090000","timestamp":1.403093881E9},{"availabilityZone":"us-east-1d","instanceType":"r3.2xlarge","productDescription":"Linux/UNIX","spotPrice":"0.064100","timestamp":1.403093594E9},{"availabilityZone":"us-east-1b","instanceType":"r3.4xlarge","productDescription":"Windows (Amazon VPC)","spotPrice":"0.672100","timestamp":1.403091818E9},{"availabilityZone":"us-east-1b","instanceType":"m3.xlarge","productDescription":"SUSE Linux","spotPrice":"0.550100","timestamp":1.403091805E9},{"availabilityZone":"us-east-1b","instanceType":"c3.2xlarge","productDescription":"Linux/UNIX (Amazon VPC)","spotPrice":"2.400000","timestamp":1.403091489E9},{"availabilityZone":"us-east-1d","instanceType":"r3.2xlarge","productDescription":"Linux/UNIX (Amazon VPC)","spotPrice":"0.064100","timestamp":1.403091485E9},{"availabilityZone":"us-east-1b","instanceType":"c3.4xlarge","productDescription":"Linux/UNIX (Amazon VPC)","spotPrice":"4.800000","timestamp":1.403091353E9},{"availabilityZone":"us-east-1b","instanceType":"c3.large","productDescription":"Windows (Amazon VPC)","spotPrice":"0.150000","timestamp":1.403091101E9},{"availabilityZone":"us-east-1d","instanceType":"cr1.8xlarge","productDescription":"SUSE Linux","spotPrice":"0.554100","timestamp":1.40309015E9},{"availabilityZone":"us-east-1b","instanceType":"c3.large","productDescription":"SUSE Linux","spotPrice":"0.250000","timestamp":1.403089936E9},{"availabilityZone":"us-east-1d","instanceType":"r3.2xlarge","productDescription":"Windows","spotPrice":"0.444100","timestamp":1.403088394E9},{"availabilityZone":"us-east-1a","instanceType":"m3.xlarge","productDescription":"SUSE Linux","spotPrice":"0.550100","timestamp":1.40308757E9},{"availabilityZone":"us-east-1a","instanceType":"r3.4xlarge","productDescription":"Linux/UNIX (Amazon VPC)","spotPrice":"0.128100","timestamp":1.403087224E9},{"availabilityZone":"us-east-1b","instanceType":"m2.xlarge","productDescription":"Linux/UNIX (Amazon VPC)","spotPrice":"0.016100","timestamp":1.403087218E9},{"availabilityZone":"us-east-1a","instanceType":"m1.xlarge","productDescription":"Linux/UNIX","spotPrice":"0.032100","timestamp":1.403086673E9},{"availabilityZone":"us-east-1a","instanceType":"r3.4xlarge","productDescription":"Linux/UNIX","spotPrice":"0.128300","timestamp":1.403086617E9},{"availabilityZone":"us-east-1a","instanceType":"r3.8xlarge","productDescription":"SUSE Linux","spotPrice":"0.364500","timestamp":1.40308451E9},{"availabilityZone":"us-east-1b","instanceType":"r3.2xlarge","productDescription":"Windows (Amazon VPC)","spotPrice":"0.444100","timestamp":1.403084274E9},{"availabilityZone":"us-east-1b","instanceType":"r3.2xlarge","productDescription":"Windows","spotPrice":"0.444100","timestamp":1.403084175E9},{"availabilityZone":"us-east-1d","instanceType":"c1.xlarge","productDescription":"Linux/UNIX (Amazon VPC)","spotPrice":"0.064100","timestamp":1.403084088E9},{"availabilityZone":"us-east-1d","instanceType":"m1.medium","productDescription":"SUSE Linux (Amazon VPC)","spotPrice":"0.019100","timestamp":1.403083989E9},{"availabilityZone":"us-east-1b","instanceType":"m1.medium","productDescription":"SUSE Linux (Amazon VPC)","spotPrice":"0.019100","timestamp":1.403083988E9},{"availabilityZone":"us-east-1d","instanceType":"m2.2xlarge","productDescription":"SUSE Linux (Amazon VPC)","spotPrice":"0.920100","timestamp":1.403083288E9},{"availabilityZone":"us-east-1a","instanceType":"t1.micro","productDescription":"SUSE Linux","spotPrice":"0.006100","timestamp":1.403081725E9},{"availabilityZone":"us-east-1d","instanceType":"c1.xlarge","productDescription":"SUSE Linux","spotPrice":"0.077100","timestamp":1.403081517E9},{"availabilityZone":"us-east-1b","instanceType":"c1.xlarge","productDescription":"SUSE Linux","spotPrice":"0.077100","timestamp":1.403081517E9},{"availabilityZone":"us-east-1d","instanceType":"hi1.4xlarge","productDescription":"SUSE Linux","spotPrice":"0.257800","timestamp":1.403081172E9},{"availabilityZone":"us-east-1b","instanceType":"c3.2xlarge","productDescription":"Windows (Amazon VPC)","spotPrice":"0.449600","timestamp":1.403081037E9},{"availabilityZone":"us-east-1d","instanceType":"m2.2xlarge","productDescription":"SUSE Linux","spotPrice":"0.920100","timestamp":1.403080857E9},{"availabilityZone":"us-east-1d","instanceType":"m1.large","productDescription":"Linux/UNIX (Amazon VPC)","spotPrice":"0.016100","timestamp":1.403079972E9},{"availabilityZone":"us-east-1b","instanceType":"c3.8xlarge","productDescription":"Linux/UNIX (Amazon VPC)","spotPrice":"9.600000","timestamp":1.403079353E9},{"availabilityZone":"us-east-1d","instanceType":"m2.xlarge","productDescription":"Windows (Amazon VPC)","spotPrice":"0.070100","timestamp":1.403079249E9},{"availabilityZone":"us-east-1a","instanceType":"r3.2xlarge","productDescription":"Linux/UNIX","spotPrice":"0.064100","timestamp":1.403078077E9},{"availabilityZone":"us-east-1a","instanceType":"c1.medium","productDescription":"SUSE Linux","spotPrice":"0.024100","timestamp":1.403077994E9},{"availabilityZone":"us-east-1d","instanceType":"m1.xlarge","productDescription":"SUSE Linux","spotPrice":"0.057100","timestamp":1.40307749E9},{"availabilityZone":"us-east-1a","instanceType":"m3.xlarge","productDescription":"Linux/UNIX (Amazon VPC)","spotPrice":"0.990000","timestamp":1.403077438E9},{"availabilityZone":"us-east-1b","instanceType":"c3.xlarge","productDescription":"Linux/UNIX (Amazon VPC)","spotPrice":"0.300100","timestamp":1.403077411E9},{"availabilityZone":"us-east-1a","instanceType":"m3.large","productDescription":"Windows","spotPrice":"0.117100","timestamp":1.403076872E9},{"availabilityZone":"us-east-1a","instanceType":"cr1.8xlarge","productDescription":"SUSE Linux (Amazon VPC)","spotPrice":"3.600100","timestamp":1.403076567E9},{"availabilityZone":"us-east-1a","instanceType":"cg1.4xlarge","productDescription":"Linux/UNIX","spotPrice":"2.100100","timestamp":1.403076319E9},{"availabilityZone":"us-east-1a","instanceType":"cr1.8xlarge","productDescription":"Linux/UNIX (Amazon VPC)","spotPrice":"0.484100","timestamp":1.403076296E9},{"availabilityZone":"us-east-1b","instanceType":"r3.4xlarge","productDescription":"Linux/UNIX (Amazon VPC)","spotPrice":"0.128100","timestamp":1.403075184E9},{"availabilityZone":"us-east-1d","instanceType":"m3.medium","productDescription":"Windows (Amazon VPC)","spotPrice":"0.059100","timestamp":1.403074351E9},{"availabilityZone":"us-east-1a","instanceType":"m2.4xlarge","productDescription":"Windows (Amazon VPC)","spotPrice":"0.280100","timestamp":1.403074272E9},{"availabilityZone":"us-east-1a","instanceType":"m2.4xlarge","productDescription":"Windows","spotPrice":"0.280100","timestamp":1.403073944E9},{"availabilityZone":"us-east-1a","instanceType":"m3.medium","productDescription":"Linux/UNIX","spotPrice":"0.452000","timestamp":1.403073779E9},{"availabilityZone":"us-east-1d","instanceType":"hi1.4xlarge","productDescription":"Linux/UNIX (Amazon VPC)","spotPrice":"0.128400","timestamp":1.403073248E9},{"availabilityZone":"us-east-1d","instanceType":"r3.large","productDescription":"Linux/UNIX (Amazon VPC)","spotPrice":"0.016100","timestamp":1.403072666E9},{"availabilityZone":"us-east-1a","instanceType":"r3.large","productDescription":"Linux/UNIX (Amazon VPC)","spotPrice":"0.016100","timestamp":1.403072665E9},{"availabilityZone":"us-east-1b","instanceType":"r3.large","productDescription":"Linux/UNIX (Amazon VPC)","spotPrice":"0.016100","timestamp":1.403072665E9},{"availabilityZone":"us-east-1d","instanceType":"r3.large","productDescription":"SUSE Linux (Amazon VPC)","spotPrice":"0.116100","timestamp":1.403072665E9},{"availabilityZone":"us-east-1a","instanceType":"r3.large","productDescription":"SUSE Linux (Amazon VPC)","spotPrice":"0.116100","timestamp":1.403072665E9},{"availabilityZone":"us-east-1a","instanceType":"m1.xlarge","productDescription":"Windows","spotPrice":"0.132100","timestamp":1.403072658E9},{"availabilityZone":"us-east-1d","instanceType":"r3.large","productDescription":"Windows","spotPrice":"0.174100","timestamp":1.403072651E9},{"availabilityZone":"us-east-1a","instanceType":"r3.large","productDescription":"Windows","spotPrice":"0.174100","timestamp":1.403072651E9},{"availabilityZone":"us-east-1b","instanceType":"r3.large","productDescription":"Windows","spotPrice":"0.174100","timestamp":1.403072651E9},{"availabilityZone":"us-east-1d","instanceType":"r3.xlarge","productDescription":"Linux/UNIX","spotPrice":"0.032100","timestamp":1.403072646E9},{"availabilityZone":"us-east-1a","instanceType":"r3.xlarge","productDescription":"Linux/UNIX","spotPrice":"0.032100","timestamp":1.403072646E9},{"availabilityZone":"us-east-1b","instanceType":"r3.xlarge","productDescription":"Linux/UNIX","spotPrice":"0.032100","timestamp":1.403072646E9},{"availabilityZone":"us-east-1d","instanceType":"r3.4xlarge","productDescription":"Windows (Amazon VPC)","spotPrice":"0.672100","timestamp":1.403072641E9},{"availabilityZone":"us-east-1a","instanceType":"r3.4xlarge","productDescription":"Windows (Amazon VPC)","spotPrice":"0.672100","timestamp":1.403072641E9},{"availabilityZone":"us-east-1d","instanceType":"r3.2xlarge","productDescription":"Windows (Amazon VPC)","spotPrice":"0.444100","timestamp":1.403072638E9},{"availabilityZone":"us-east-1d","instanceType":"r3.xlarge","productDescription":"Windows (Amazon VPC)","spotPrice":"0.282100","timestamp":1.4030726E9},{"availabilityZone":"us-east-1a","instanceType":"r3.xlarge","productDescription":"Windows (Amazon VPC)","spotPrice":"0.282100","timestamp":1.4030726E9},{"availabilityZone":"us-east-1b","instanceType":"r3.xlarge","productDescription":"Windows (Amazon VPC)","spotPrice":"0.282100","timestamp":1.4030726E9},{"availabilityZone":"us-east-1a","instanceType":"r3.2xlarge","productDescription":"Linux/UNIX (Amazon VPC)","spotPrice":"0.064100","timestamp":1.403072596E9},{"availabilityZone":"us-east-1d","instanceType":"r3.xlarge","productDescription":"Linux/UNIX (Amazon VPC)","spotPrice":"0.032100","timestamp":1.403072566E9},{"availabilityZone":"us-east-1a","instanceType":"r3.xlarge","productDescription":"Linux/UNIX (Amazon VPC)","spotPrice":"0.032100","timestamp":1.403072566E9},{"availabilityZone":"us-east-1b","instanceType":"r3.xlarge","productDescription":"Linux/UNIX (Amazon VPC)","spotPrice":"0.032100","timestamp":1.403072566E9},{"availabilityZone":"us-east-1d","instanceType":"r3.4xlarge","productDescription":"Windows","spotPrice":"0.672100","timestamp":1.403072564E9},{"availabilityZone":"us-east-1a","instanceType":"r3.4xlarge","productDescription":"Windows","spotPrice":"0.672100","timestamp":1.403072563E9},{"availabilityZone":"us-east-1a","instanceType":"r3.2xlarge","productDescription":"Windows","spotPrice":"0.444100","timestamp":1.403072551E9},{"availabilityZone":"us-east-1d","instanceType":"m1.medium","productDescription":"Linux/UNIX (Amazon VPC)","spotPrice":"0.008100","timestamp":1.403072372E9},{"availabilityZone":"us-east-1d","instanceType":"r3.xlarge","productDescription":"Windows","spotPrice":"0.282100","timestamp":1.403071636E9},{"availabilityZone":"us-east-1a","instanceType":"r3.xlarge","productDescription":"Windows","spotPrice":"0.282100","timestamp":1.403071636E9},{"availabilityZone":"us-east-1b","instanceType":"r3.xlarge","productDescription":"Windows","spotPrice":"0.282100","timestamp":1.403071636E9},{"availabilityZone":"us-east-1a","instanceType":"r3.large","productDescription":"SUSE Linux","spotPrice":"0.116100","timestamp":1.403071629E9},{"availabilityZone":"us-east-1d","instanceType":"r3.large","productDescription":"Linux/UNIX","spotPrice":"0.016100","timestamp":1.403071628E9},{"availabilityZone":"us-east-1a","instanceType":"r3.large","productDescription":"Linux/UNIX","spotPrice":"0.016100","timestamp":1.403071628E9},{"availabilityZone":"us-east-1b","instanceType":"r3.large","productDescription":"Linux/UNIX","spotPrice":"0.016100","timestamp":1.403071628E9},{"availabilityZone":"us-east-1d","instanceType":"r3.large","productDescription":"Windows (Amazon VPC)","spotPrice":"0.174100","timestamp":1.403071626E9},{"availabilityZone":"us-east-1a","instanceType":"r3.large","productDescription":"Windows (Amazon VPC)","spotPrice":"0.174100","timestamp":1.403071626E9},{"availabilityZone":"us-east-1b","instanceType":"r3.large","productDescription":"Windows (Amazon VPC)","spotPrice":"0.174100","timestamp":1.403071626E9},{"availabilityZone":"us-east-1a","instanceType":"m1.xlarge","productDescription":"SUSE Linux (Amazon VPC)","spotPrice":"0.057100","timestamp":1.40307082E9},{"availabilityZone":"us-east-1a","instanceType":"m2.xlarge","productDescription":"Windows (Amazon VPC)","spotPrice":"0.070100","timestamp":1.403070632E9},{"availabilityZone":"us-east-1d","instanceType":"m1.xlarge","productDescription":"SUSE Linux (Amazon VPC)","spotPrice":"0.057100","timestamp":1.403069717E9},{"availabilityZone":"us-east-1d","instanceType":"m1.xlarge","productDescription":"Windows","spotPrice":"0.132100","timestamp":1.403068667E9},{"availabilityZone":"us-east-1a","instanceType":"m3.medium","productDescription":"Linux/UNIX (Amazon VPC)","spotPrice":"0.452000","timestamp":1.403068473E9},{"availabilityZone":"us-east-1d","instanceType":"m2.xlarge","productDescription":"SUSE Linux","spotPrice":"0.042200","timestamp":1.403067915E9},{"availabilityZone":"us-east-1d","instanceType":"m3.medium","productDescription":"SUSE Linux (Amazon VPC)","spotPrice":"0.108100","timestamp":1.403067255E9},{"availabilityZone":"us-east-1d","instanceType":"c1.xlarge","productDescription":"Windows (Amazon VPC)","spotPrice":"0.200100","timestamp":1.403067166E9},{"availabilityZone":"us-east-1b","instanceType":"cc2.8xlarge","productDescription":"Windows (Amazon VPC)","spotPrice":"0.428100","timestamp":1.40306716E9},{"availabilityZone":"us-east-1d","instanceType":"m1.large","productDescription":"Windows (Amazon VPC)","spotPrice":"0.066100","timestamp":1.403067143E9},{"availabilityZone":"us-east-1a","instanceType":"m1.large","productDescription":"Windows (Amazon VPC)","spotPrice":"0.066100","timestamp":1.403067143E9},{"availabilityZone":"us-east-1b","instanceType":"m1.large","productDescription":"Windows (Amazon VPC)","spotPrice":"0.066100","timestamp":1.403067143E9},{"availabilityZone":"us-east-1d","instanceType":"m1.small","productDescription":"Windows (Amazon VPC)","spotPrice":"0.017100","timestamp":1.40306714E9},{"availabilityZone":"us-east-1a","instanceType":"m1.small","productDescription":"Windows (Amazon VPC)","spotPrice":"0.017100","timestamp":1.40306714E9},{"availabilityZone":"us-east-1b","instanceType":"m1.small","productDescription":"Windows (Amazon VPC)","spotPrice":"0.017100","timestamp":1.40306714E9},{"availabilityZone":"us-east-1d","instanceType":"t1.micro","productDescription":"Windows (Amazon VPC)","spotPrice":"0.006100","timestamp":1.403067113E9},{"availabilityZone":"us-east-1a","instanceType":"t1.micro","productDescription":"Windows (Amazon VPC)","spotPrice":"0.006100","timestamp":1.403067113E9},{"availabilityZone":"us-east-1b","instanceType":"t1.micro","productDescription":"Windows (Amazon VPC)","spotPrice":"0.006100","timestamp":1.403067113E9},{"availabilityZone":"us-east-1d","instanceType":"t1.micro","productDescription":"Windows","spotPrice":"0.006100","timestamp":1.403067106E9},{"availabilityZone":"us-east-1a","instanceType":"t1.micro","productDescription":"Windows","spotPrice":"0.006100","timestamp":1.403067106E9},{"availabilityZone":"us-east-1b","instanceType":"t1.micro","productDescription":"Windows","spotPrice":"0.006100","timestamp":1.403067106E9},{"availabilityZone":"us-east-1d","instanceType":"m1.medium","productDescription":"Windows","spotPrice":"0.033100","timestamp":1.403067095E9},{"availabilityZone":"us-east-1a","instanceType":"m1.medium","productDescription":"Windows","spotPrice":"0.033100","timestamp":1.403067095E9},{"availabilityZone":"us-east-1b","instanceType":"m1.medium","productDescription":"Windows","spotPrice":"0.033100","timestamp":1.403067095E9},{"availabilityZone":"us-east-1d","instanceType":"c1.xlarge","productDescription":"Windows","spotPrice":"0.200100","timestamp":1.403067067E9},{"availabilityZone":"us-east-1d","instanceType":"m1.medium","productDescription":"Windows (Amazon VPC)","spotPrice":"0.033100","timestamp":1.403067051E9},{"availabilityZone":"us-east-1a","instanceType":"m1.medium","productDescription":"Windows (Amazon VPC)","spotPrice":"0.033100","timestamp":1.403067051E9},{"availabilityZone":"us-east-1b","instanceType":"m1.medium","productDescription":"Windows (Amazon VPC)","spotPrice":"0.033100","timestamp":1.40306705E9},{"availabilityZone":"us-east-1b","instanceType":"m1.xlarge","productDescription":"Windows (Amazon VPC)","spotPrice":"0.132100","timestamp":1.403067048E9},{"availabilityZone":"us-east-1a","instanceType":"cg1.4xlarge","productDescription":"SUSE Linux","spotPrice":"2.200100","timestamp":1.403067039E9},{"availabilityZone":"us-east-1d","instanceType":"c1.medium","productDescription":"Windows (Amazon VPC)","spotPrice":"0.050100","timestamp":1.403066693E9},{"availabilityZone":"us-east-1d","instanceType":"m1.large","productDescription":"Windows","spotPrice":"0.066100","timestamp":1.403066391E9},{"availabilityZone":"us-east-1a","instanceType":"m1.large","productDescription":"Windows","spotPrice":"0.066100","timestamp":1.403066391E9},{"availabilityZone":"us-east-1b","instanceType":"m1.large","productDescription":"Windows","spotPrice":"0.066100","timestamp":1.403066391E9},{"availabilityZone":"us-east-1d","instanceType":"m1.small","productDescription":"Windows","spotPrice":"0.017100","timestamp":1.403066387E9},{"availabilityZone":"us-east-1a","instanceType":"m1.small","productDescription":"Windows","spotPrice":"0.017100","timestamp":1.403066387E9},{"availabilityZone":"us-east-1b","instanceType":"m1.small","productDescription":"Windows","spotPrice":"0.017100","timestamp":1.403066387E9},{"availabilityZone":"us-east-1a","instanceType":"m1.large","productDescription":"SUSE Linux","spotPrice":"0.032100","timestamp":1.40306597E9},{"availabilityZone":"us-east-1b","instanceType":"m1.large","productDescription":"SUSE Linux","spotPrice":"0.032100","timestamp":1.40306597E9},{"availabilityZone":"us-east-1a","instanceType":"m1.xlarge","productDescription":"SUSE Linux","spotPrice":"0.057100","timestamp":1.403065644E9},{"availabilityZone":"us-east-1b","instanceType":"c3.xlarge","productDescription":"Windows","spotPrice":"0.224800","timestamp":1.403065616E9},{"availabilityZone":"us-east-1a","instanceType":"r3.8xlarge","productDescription":"Windows","spotPrice":"0.956100","timestamp":1.403065564E9},{"availabilityZone":"us-east-1d","instanceType":"t1.micro","productDescription":"Linux/UNIX","spotPrice":"0.003100","timestamp":1.403064873E9},{"availabilityZone":"us-east-1a","instanceType":"m1.xlarge","productDescription":"Windows (Amazon VPC)","spotPrice":"0.132100","timestamp":1.403064344E9},{"availabilityZone":"us-east-1a","instanceType":"c3.xlarge","productDescription":"Windows (Amazon VPC)","spotPrice":"0.198100","timestamp":1.403063839E9},{"availabilityZone":"us-east-1d","instanceType":"m1.large","productDescription":"SUSE Linux (Amazon VPC)","spotPrice":"0.032100","timestamp":1.403063335E9},{"availabilityZone":"us-east-1a","instanceType":"c1.xlarge","productDescription":"Windows","spotPrice":"0.200100","timestamp":1.403062828E9},{"availabilityZone":"us-east-1b","instanceType":"cc1.4xlarge","productDescription":"Windows","spotPrice":"0.628100","timestamp":1.403062748E9},{"availabilityZone":"us-east-1b","instanceType":"c3.large","productDescription":"Windows","spotPrice":"0.155700","timestamp":1.403061116E9},{"availabilityZone":"us-east-1b","instanceType":"m3.large","productDescription":"Windows (Amazon VPC)","spotPrice":"0.117100","timestamp":1.403061072E9},{"availabilityZone":"us-east-1a","instanceType":"c3.large","productDescription":"Linux/UNIX (Amazon VPC)","spotPrice":"0.016100","timestamp":1.403060206E9},{"availabilityZone":"us-east-1b","instanceType":"c3.8xlarge","productDescription":"SUSE Linux","spotPrice":"2.500000","timestamp":1.4030602E9},{"availabilityZone":"us-east-1d","instanceType":"m1.medium","productDescription":"SUSE Linux","spotPrice":"0.019100","timestamp":1.403060168E9},{"availabilityZone":"us-east-1b","instanceType":"m1.xlarge","productDescription":"Windows","spotPrice":"0.132100","timestamp":1.403059918E9},{"availabilityZone":"us-east-1a","instanceType":"r3.8xlarge","productDescription":"Windows (Amazon VPC)","spotPrice":"0.956100","timestamp":1.40305964E9},{"availabilityZone":"us-east-1a","instanceType":"c3.large","productDescription":"Windows","spotPrice":"0.104100","timestamp":1.403059618E9},{"availabilityZone":"us-east-1d","instanceType":"c3.xlarge","productDescription":"Windows","spotPrice":"0.198100","timestamp":1.403059565E9},{"availabilityZone":"us-east-1a","instanceType":"c3.xlarge","productDescription":"Windows","spotPrice":"0.198100","timestamp":1.403059565E9},{"availabilityZone":"us-east-1b","instanceType":"c3.4xlarge","productDescription":"SUSE Linux (Amazon VPC)","spotPrice":"1.300100","timestamp":1.403059438E9},{"availabilityZone":"us-east-1b","instanceType":"c3.4xlarge","productDescription":"SUSE Linux","spotPrice":"1.300100","timestamp":1.403059237E9},{"availabilityZone":"us-east-1b","instanceType":"m2.4xlarge","productDescription":"Windows (Amazon VPC)","spotPrice":"0.280100","timestamp":1.403058904E9},{"availabilityZone":"us-east-1a","instanceType":"m3.2xlarge","productDescription":"Windows (Amazon VPC)","spotPrice":"0.557300","timestamp":1.403058731E9},{"availabilityZone":"us-east-1a","instanceType":"c3.large","productDescription":"Windows (Amazon VPC)","spotPrice":"0.104100","timestamp":1.40305821E9},{"availabilityZone":"us-east-1b","instanceType":"m3.large","productDescription":"Linux/UNIX","spotPrice":"0.630000","timestamp":1.403058021E9},{"availabilityZone":"us-east-1b","instanceType":"m1.xlarge","productDescription":"Linux/UNIX (Amazon VPC)","spotPrice":"0.032100","timestamp":1.403057914E9},{"availabilityZone":"us-east-1d","instanceType":"cr1.8xlarge","productDescription":"SUSE Linux (Amazon VPC)","spotPrice":"3.600100","timestamp":1.403057858E9},{"availabilityZone":"us-east-1b","instanceType":"cr1.8xlarge","productDescription":"SUSE Linux (Amazon VPC)","spotPrice":"3.600100","timestamp":1.403057858E9},{"availabilityZone":"us-east-1d","instanceType":"m3.large","productDescription":"Windows (Amazon VPC)","spotPrice":"0.117100","timestamp":1.403056961E9},{"availabilityZone":"us-east-1b","instanceType":"m3.large","productDescription":"Windows","spotPrice":"0.150000","timestamp":1.40305692E9},{"availabilityZone":"us-east-1a","instanceType":"hi1.4xlarge","productDescription":"Windows (Amazon VPC)","spotPrice":"0.481100","timestamp":1.403056623E9},{"availabilityZone":"us-east-1d","instanceType":"m3.medium","productDescription":"Linux/UNIX (Amazon VPC)","spotPrice":"0.008100","timestamp":1.403056211E9},{"availabilityZone":"us-east-1a","instanceType":"cg1.4xlarge","productDescription":"SUSE Linux (Amazon VPC)","spotPrice":"2.200100","timestamp":1.403055488E9},{"availabilityZone":"us-east-1b","instanceType":"r3.8xlarge","productDescription":"Windows","spotPrice":"0.956100","timestamp":1.403055395E9},{"availabilityZone":"us-east-1a","instanceType":"m1.xlarge","productDescription":"Linux/UNIX (Amazon VPC)","spotPrice":"0.032100","timestamp":1.403055085E9},{"availabilityZone":"us-east-1b","instanceType":"t1.micro","productDescription":"SUSE Linux","spotPrice":"0.006100","timestamp":1.403054977E9},{"availabilityZone":"us-east-1b","instanceType":"c3.large","productDescription":"SUSE Linux (Amazon VPC)","spotPrice":"0.250000","timestamp":1.40305487E9},{"availabilityZone":"us-east-1b","instanceType":"cc1.4xlarge","productDescription":"Linux/UNIX","spotPrice":"0.128200","timestamp":1.403054676E9},{"availabilityZone":"us-east-1a","instanceType":"m3.xlarge","productDescription":"Windows","spotPrice":"0.279100","timestamp":1.403054229E9},{"availabilityZone":"us-east-1a","instanceType":"m3.xlarge","productDescription":"Windows (Amazon VPC)","spotPrice":"0.702000","timestamp":1.403054173E9},{"availabilityZone":"us-east-1d","instanceType":"c3.large","productDescription":"SUSE Linux","spotPrice":"0.116100","timestamp":1.403054111E9},{"availabilityZone":"us-east-1b","instanceType":"m1.medium","productDescription":"SUSE Linux","spotPrice":"0.019100","timestamp":1.40305355E9},{"availabilityZone":"us-east-1a","instanceType":"m1.medium","productDescription":"SUSE Linux (Amazon VPC)","spotPrice":"0.019100","timestamp":1.403052665E9},{"availabilityZone":"us-east-1d","instanceType":"m3.2xlarge","productDescription":"Windows (Amazon VPC)","spotPrice":"0.275100","timestamp":1.403052352E9},{"availabilityZone":"us-east-1a","instanceType":"c3.xlarge","productDescription":"Linux/UNIX (Amazon VPC)","spotPrice":"0.032100","timestamp":1.403052212E9},{"availabilityZone":"us-east-1a","instanceType":"m1.medium","productDescription":"Linux/UNIX","spotPrice":"0.008100","timestamp":1.403050741E9},{"availabilityZone":"us-east-1b","instanceType":"c1.medium","productDescription":"Windows (Amazon VPC)","spotPrice":"0.050100","timestamp":1.403050611E9},{"availabilityZone":"us-east-1b","instanceType":"c3.4xlarge","productDescription":"Windows (Amazon VPC)","spotPrice":"0.834900","timestamp":1.403050433E9},{"availabilityZone":"us-east-1b","instanceType":"c3.4xlarge","productDescription":"Windows","spotPrice":"0.834900","timestamp":1.403050419E9},{"availabilityZone":"us-east-1d","instanceType":"m1.xlarge","productDescription":"Windows (Amazon VPC)","spotPrice":"0.132100","timestamp":1.403050354E9},{"availabilityZone":"us-east-1b","instanceType":"hi1.4xlarge","productDescription":"Windows","spotPrice":"0.481100","timestamp":1.403050128E9},{"availabilityZone":"us-east-1d","instanceType":"m1.xlarge","productDescription":"Linux/UNIX (Amazon VPC)","spotPrice":"0.032100","timestamp":1.403050079E9},{"availabilityZone":"us-east-1b","instanceType":"r3.8xlarge","productDescription":"Windows (Amazon VPC)","spotPrice":"0.956100","timestamp":1.403049873E9},{"availabilityZone":"us-east-1b","instanceType":"m1.medium","productDescription":"Linux/UNIX","spotPrice":"0.008100","timestamp":1.403049818E9},{"availabilityZone":"us-east-1a","instanceType":"c3.2xlarge","productDescription":"Windows (Amazon VPC)","spotPrice":"0.396100","timestamp":1.403049253E9},{"availabilityZone":"us-east-1d","instanceType":"c1.xlarge","productDescription":"SUSE Linux (Amazon VPC)","spotPrice":"0.077100","timestamp":1.403048748E9},{"availabilityZone":"us-east-1d","instanceType":"t1.micro","productDescription":"SUSE Linux (Amazon VPC)","spotPrice":"0.006100","timestamp":1.403046794E9},{"availabilityZone":"us-east-1a","instanceType":"c1.xlarge","productDescription":"SUSE Linux","spotPrice":"0.077100","timestamp":1.403046762E9},{"availabilityZone":"us-east-1d","instanceType":"r3.8xlarge","productDescription":"Windows","spotPrice":"0.956100","timestamp":1.40304642E9},{"availabilityZone":"us-east-1d","instanceType":"g2.2xlarge","productDescription":"Linux/UNIX (Amazon VPC)","spotPrice":"0.082321","timestamp":1.403046161E9},{"availabilityZone":"us-east-1b","instanceType":"r3.2xlarge","productDescription":"SUSE Linux (Amazon VPC)","spotPrice":"0.164500","timestamp":1.403045868E9},{"availabilityZone":"us-east-1a","instanceType":"c3.large","productDescription":"SUSE Linux","spotPrice":"0.116100","timestamp":1.403045821E9},{"availabilityZone":"us-east-1b","instanceType":"r3.2xlarge","productDescription":"Linux/UNIX","spotPrice":"0.064100","timestamp":1.403045605E9},{"availabilityZone":"us-east-1a","instanceType":"m3.large","productDescription":"Linux/UNIX (Amazon VPC)","spotPrice":"0.150000","timestamp":1.403045289E9},{"availabilityZone":"us-east-1a","instanceType":"cc2.8xlarge","productDescription":"Windows (Amazon VPC)","spotPrice":"0.428100","timestamp":1.403045016E9},{"availabilityZone":"us-east-1a","instanceType":"c3.large","productDescription":"SUSE Linux (Amazon VPC)","spotPrice":"0.116100","timestamp":1.403045003E9},{"availabilityZone":"us-east-1a","instanceType":"hi1.4xlarge","productDescription":"Windows","spotPrice":"0.481100","timestamp":1.403044969E9},{"availabilityZone":"us-east-1d","instanceType":"m1.small","productDescription":"Linux/UNIX (Amazon VPC)","spotPrice":"0.007100","timestamp":1.40304496E9},{"availabilityZone":"us-east-1a","instanceType":"m1.small","productDescription":"Linux/UNIX (Amazon VPC)","spotPrice":"0.007100","timestamp":1.40304496E9},{"availabilityZone":"us-east-1b","instanceType":"hi1.4xlarge","productDescription":"SUSE Linux","spotPrice":"0.232400","timestamp":1.403044847E9},{"availabilityZone":"us-east-1b","instanceType":"m1.small","productDescription":"SUSE Linux","spotPrice":"0.360000","timestamp":1.403044844E9},{"availabilityZone":"us-east-1b","instanceType":"m1.small","productDescription":"Linux/UNIX","spotPrice":"0.240000","timestamp":1.403044843E9},{"availabilityZone":"us-east-1b","instanceType":"c1.xlarge","productDescription":"SUSE Linux (Amazon VPC)","spotPrice":"0.077200","timestamp":1.403044795E9},{"availabilityZone":"us-east-1d","instanceType":"r3.8xlarge","productDescription":"Windows (Amazon VPC)","spotPrice":"0.956100","timestamp":1.403044713E9},{"availabilityZone":"us-east-1d","instanceType":"hi1.4xlarge","productDescription":"Windows","spotPrice":"0.481100","timestamp":1.403044666E9},{"availabilityZone":"us-east-1d","instanceType":"hi1.4xlarge","productDescription":"Windows (Amazon VPC)","spotPrice":"0.481100","timestamp":1.403044607E9},{"availabilityZone":"us-east-1d","instanceType":"c3.large","productDescription":"Windows (Amazon VPC)","spotPrice":"0.104100","timestamp":1.403044198E9},{"availabilityZone":"us-east-1a","instanceType":"m3.xlarge","productDescription":"Linux/UNIX","spotPrice":"0.500000","timestamp":1.403044029E9},{"availabilityZone":"us-east-1d","instanceType":"m1.small","productDescription":"SUSE Linux","spotPrice":"0.013100","timestamp":1.403042946E9},{"availabilityZone":"us-east-1a","instanceType":"m1.small","productDescription":"SUSE Linux","spotPrice":"0.013100","timestamp":1.403042946E9},{"availabilityZone":"us-east-1a","instanceType":"cc1.4xlarge","productDescription":"Windows","spotPrice":"0.628100","timestamp":1.403042935E9},{"availabilityZone":"us-east-1b","instanceType":"c3.xlarge","productDescription":"Linux/UNIX","spotPrice":"0.210000","timestamp":1.403041451E9},{"availabilityZone":"us-east-1b","instanceType":"c3.xlarge","productDescription":"Windows (Amazon VPC)","spotPrice":"0.208800","timestamp":1.403041434E9},{"availabilityZone":"us-east-1b","instanceType":"cr1.8xlarge","productDescription":"SUSE Linux","spotPrice":"3.600100","timestamp":1.403041227E9},{"availabilityZone":"us-east-1d","instanceType":"c3.large","productDescription":"Linux/UNIX (Amazon VPC)","spotPrice":"0.016100","timestamp":1.403041116E9},{"availabilityZone":"us-east-1b","instanceType":"m3.medium","productDescription":"Windows (Amazon VPC)","spotPrice":"0.300000","timestamp":1.403041082E9},{"availabilityZone":"us-east-1b","instanceType":"r3.xlarge","productDescription":"SUSE Linux (Amazon VPC)","spotPrice":"0.132400","timestamp":1.403040649E9},{"availabilityZone":"us-east-1a","instanceType":"cg1.4xlarge","productDescription":"Windows","spotPrice":"1.050000","timestamp":1.39951279E9},{"availabilityZone":"us-east-1b","instanceType":"cg1.4xlarge","productDescription":"Windows","spotPrice":"1.050100","timestamp":1.399512782E9}]}
